pathimport/__init__.py
pathimport/pathimport.py
pathimport-0.0.4.dist-info/METADATA
pathimport-0.0.4.dist-info/WHEEL
pathimport-0.0.4.dist-info/top_level.txt
pathimport-0.0.4.dist-info/RECORD
