Metadata-Version: 2.1
Name: pathimport
Version: 0.0.4
Summary: Python imports without the headache
Home-page: https://github.com/FedericoDiMarzo/pathimport
Author: Federico Di Marzo
Author-email: federicodimarzo@protonmail.com
Project-URL: Bug Tracker, https://github.com/FedericoDiMarzo/pathimport/issues
Classifier: Programming Language :: Python :: 3
Classifier: License :: OSI Approved :: MIT License
Classifier: Operating System :: OS Independent
Requires-Python: >=3.5
